alina/__init__.py
alina/interface.py
alina/irena/__init__.py
alina/irena/client.py
alina/irena/factories.py
alina/irena/parsers/containers.py
alina/irena/parsers/responses.py
alina/irena/requests.py
alina/tools/__init__.py
alina/tools/expressions.py
alina_api-0.1.0.dist-info/LICENSE.md
alina_api-0.1.0.dist-info/WHEEL
alina_api-0.1.0.dist-info/METADATA
alina_api-0.1.0.dist-info/RECORD
