Metadata-Version: 2.1
Name: alina-api
Version: 0.1.0
Summary: irena1.intercity.pl API for intercity employees.
License: MIT
Author: Konrad Nowara
Requires-Python: >=3.9,<4.0
Classifier: License :: OSI Approved :: MIT License
Classifier: Programming Language :: Python :: 3
Classifier: Programming Language :: Python :: 3.10
Classifier: Programming Language :: Python :: 3.9
